pystreamtape/__init__.py
pystreamtape/streamtape.py
PyStreamtape-1.0.0.dist-info/LICENSE
PyStreamtape-1.0.0.dist-info/METADATA
PyStreamtape-1.0.0.dist-info/WHEEL
PyStreamtape-1.0.0.dist-info/top_level.txt
PyStreamtape-1.0.0.dist-info/RECORD
