Metadata-Version: 2.1
Name: PyStreamtape
Version: 1.0.0
Summary: Unofficial Streamtape API Wrapper for Python by Swadhin Biswas
Home-page: https://github.com/swadhinbiswas/Streamtape
Author: Swadhin Biswas
Author-email: swadhinbiswas.cse@gmail.com
Keywords: api,streamtape,video,hosting
Classifier: Development Status :: 5 - Production/Stable
Classifier: Intended Audience :: Developers
Classifier: License :: OSI Approved :: MIT License
Classifier: Programming Language :: Python :: 3
Classifier: Programming Language :: Python :: 3.6
Classifier: Programming Language :: Python :: 3.7
Classifier: Programming Language :: Python :: 3.8
Classifier: Programming Language :: Python :: 3.9
Classifier: Programming Language :: Python :: 3.10
Classifier: Operating System :: OS Independent
License-File: LICENSE
Requires-Dist: requests
